{
  "meta": {
    "title": "Week 12 語句（読みつき）",
    "source": "week12.pdf"
  },
  "days": [
    {
      "id": "DAY1",
      "label": "DAY 1",
      "items": [
        {
          "term": "手順",
          "reading": "てじゅん",
          "meaning": "物事を行う順序や段取り。",
          "example": "作業の手順を確認する。"
        },
        {
          "term": "連想",
          "reading": "れんそう",
          "meaning": "ある事柄から、それに関連する他の事柄を思い浮かべること。",
          "example": "赤い色からリンゴを連想する。"
        },
        {
          "term": "食ってかかる",
          "reading": "くってかかる",
          "meaning": "激しい勢いで文句を言ったり反抗したりする。",
          "example": "判定に不満で審判に食ってかかる。"
        },
        {
          "term": "口振り",
          "reading": "くちぶり",
          "meaning": "話し方や言い方。",
          "example": "彼の口振りからは自信が感じられる。"
        },
        {
          "term": "手玉に取る",
          "reading": "てだまにとる",
          "meaning": "人を自分の思い通りに操る。",
          "example": "相手をうまく手玉に取って交渉を進める。"
        },
        {
          "term": "病み上がり",
          "reading": "やみあがり",
          "meaning": "病気が治ったばかりで、体力が回復していない状態。",
          "example": "病み上がりなので無理は禁物だ。"
        },
        {
          "term": "立て続け",
          "reading": "たてつづけ",
          "meaning": "物事が続いて起こること。",
          "example": "立て続けに不運に見舞われる。"
        },
        {
          "term": "万能",
          "reading": "ばんのう",
          "meaning": "あらゆることに優れていること。何でもできること。",
          "example": "彼はスポーツ万能な選手だ。"
        },
        {
          "term": "顔から火が出る",
          "reading": "かおからひがでる",
          "meaning": "恥ずかしくて顔が真っ赤になる。",
          "example": "人前で言い間違いをして、顔から火が出る思いだった。"
        },
        {
          "term": "早春",
          "reading": "そうしゅん",
          "meaning": "春の初め。",
          "example": "早春の風が心地よい。"
        },
        {
          "term": "おおっぴら",
          "reading": "おおっぴら",
          "meaning": "人目を気にせず、隠さない様子。",
          "example": "秘密だったことをおおっぴらに話す。"
        },
        {
          "term": "にぎわう",
          "reading": "にぎわう",
          "meaning": "人が集まってにぎやかになる。",
          "example": "休日の公園は家族連れでにぎわっている。"
        }
      ]
    },
    {
      "id": "DAY2",
      "label": "DAY 2",
      "items": [
        {
          "term": "一存",
          "reading": "いちぞん",
          "meaning": "自分一人の考え。独断。",
          "example": "私の一存では決められない。"
        },
        {
          "term": "何食わぬ顔",
          "reading": "なにくわぬかお",
          "meaning": "知っているのに知らないふりをすること。",
          "example": "彼は何食わぬ顔で嘘をついた。"
        },
        {
          "term": "目に浮かぶ",
          "reading": "めにうかぶ",
          "meaning": "過去の出来事や人の姿が、目の前にあるかのように思い出される。",
          "example": "故郷の風景が目に浮かぶ。"
        },
        {
          "term": "悪気",
          "reading": "わるぎ",
          "meaning": "害を与えようとする悪い心。",
          "example": "彼に悪気はなかったようだ。"
        },
        {
          "term": "偽造",
          "reading": "ぎぞう",
          "meaning": "本物と似せて偽物を作ること。",
          "example": "パスポートを偽造するのは犯罪だ。"
        },
        {
          "term": "反発",
          "reading": "はんぱつ",
          "meaning": "他人の意見などを受け入れずに逆らうこと。",
          "example": "親の干渉に反発する。"
        },
        {
          "term": "心を奪われる",
          "reading": "こころをうばわれる",
          "meaning": "あることに夢中になる。魅了される。",
          "example": "美しい絵画に心を奪われる。"
        },
        {
          "term": "属する",
          "reading": "ぞくする",
          "meaning": "ある団体や種類の一部であること。",
          "example": "クジラは哺乳類に属する。"
        },
        {
          "term": "そそくさと",
          "reading": "そそくさと",
          "meaning": "あわただしく、落ち着かない様子。",
          "example": "用事を済ませてそそくさと帰った。"
        },
        {
          "term": "厳か",
          "reading": "おごそか",
          "meaning": "重々しく、威厳がある様子。",
          "example": "厳かな雰囲気で式が行われた。"
        },
        {
          "term": "小手調べ",
          "reading": "こてしらべ",
          "meaning": "本格的に始める前に、少し試してみること。",
          "example": "まずは小手調べに練習問題を解く。"
        },
        {
          "term": "もどかしい",
          "reading": "もどかしい",
          "meaning": "思い通りにならなくて、じれったい。",
          "example": "言葉が通じなくてもどかしい。"
        }
      ]
    },
    {
      "id": "DAY3",
      "label": "DAY 3",
      "items": [
        {
          "term": "けじめ",
          "reading": "けじめ",
          "meaning": "区別。区切り。",
          "example": "公私のけじめをつける。"
        },
        {
          "term": "加減",
          "reading": "かげん",
          "meaning": "程よくなるように調節すること。具合。",
          "example": "お風呂の湯加減をみる。"
        },
        {
          "term": "メカニズム",
          "reading": "めかにずむ",
          "meaning": "仕組み。装置の構造。",
          "example": "地震が発生するメカニズムを研究する。"
        },
        {
          "term": "腕をふるう",
          "reading": "うでをふるう",
          "meaning": "持っている技術や才能を十分に発揮する。",
          "example": "得意の料理で腕をふるう。"
        },
        {
          "term": "夜更かし",
          "reading": "よふかし",
          "meaning": "夜遅くまで起きていること。",
          "example": "昨日は夜更かしをして眠い。"
        },
        {
          "term": "あえぐ",
          "reading": "あえぐ",
          "meaning": "苦しそうに息をする。",
          "example": "急な坂道を登ってあえぐ。"
        },
        {
          "term": "専用",
          "reading": "せんよう",
          "meaning": "特定の対象だけが使うこと。",
          "example": "ここは女性専用の車両です。"
        },
        {
          "term": "ともすれば",
          "reading": "ともすれば",
          "meaning": "どうかすると。ややもすれば。そういう傾向になりがちである。",
          "example": "初心者はともすれば基本を忘れがちだ。"
        },
        {
          "term": "ことさら",
          "reading": "ことさら",
          "meaning": "わざと。特に。",
          "example": "ことさら大声で話す必要はない。"
        },
        {
          "term": "有り得る",
          "reading": "ありうる",
          "meaning": "ある可能性がある。考えられる。",
          "example": "そんな事故は十分に有り得る。"
        },
        {
          "term": "意図",
          "reading": "いと",
          "meaning": "何かをしようとする考え。ねらい。",
          "example": "作者の意図を読み取る。"
        },
        {
          "term": "しぐさ",
          "reading": "しぐさ",
          "meaning": "ちょっとした動作や身振り。",
          "example": "彼女の髪をかき上げるしぐさが好きだ。"
        }
      ]
    },
    {
      "id": "DAY4",
      "label": "DAY 4",
      "items": [
        {
          "term": "出払う",
          "reading": "ではらう",
          "meaning": "全員が外に出て、誰もいなくなる。",
          "example": "営業部の人はみんな出払っている。"
        },
        {
          "term": "青筋を立てる",
          "reading": "あおすじをたてる",
          "meaning": "激しく怒る。",
          "example": "父は青筋を立てて怒鳴った。"
        },
        {
          "term": "頭が切れる",
          "reading": "あたまがきれる",
          "meaning": "頭の回転が速く、鋭い。",
          "example": "彼は非常に頭が切れるビジネスマンだ。"
        },
        {
          "term": "誠実",
          "reading": "せいじつ",
          "meaning": "まじめで真心があること。",
          "example": "彼は誰に対しても誠実に対応する。"
        },
        {
          "term": "取り繕う",
          "reading": "とりつくろう",
          "meaning": "不都合なところを隠して、体裁を整える。",
          "example": "笑顔でその場を取り繕う。"
        },
        {
          "term": "いたずらに",
          "reading": "いたずらに",
          "meaning": "無駄に。むやみに。",
          "example": "いたずらに時間を浪費してしまった。"
        },
        {
          "term": "こじつけ",
          "reading": "こじつけ",
          "meaning": "関係のないことを無理に関係づけること。",
          "example": "それはただのこじつけに過ぎない。"
        },
        {
          "term": "握力",
          "reading": "あくりょく",
          "meaning": "物を握りしめる力。",
          "example": "トレーニングで握力を鍛える。"
        },
        {
          "term": "度忘れ",
          "reading": "どわすれ",
          "meaning": "知っているはずのことを、ふと忘れてしまうこと。",
          "example": "知り合いの名前を度忘れしてしまった。"
        },
        {
          "term": "提案",
          "reading": "ていあん",
          "meaning": "考えや案を出すこと。",
          "example": "新しい企画を提案する。"
        },
        {
          "term": "忠告",
          "reading": "ちゅうこく",
          "meaning": "相手のためを思って注意すること。",
          "example": "友人の忠告を素直に聞く。"
        },
        {
          "term": "一躍",
          "reading": "いちやく",
          "meaning": "一気に。ひと思いに。",
          "example": "その作品で彼は一躍有名になった。"
        }
      ]
    },
    {
      "id": "DAY5",
      "label": "DAY 5",
      "items": [
        {
          "term": "余地",
          "reading": "よち",
          "meaning": "ゆとり。まだ何かできる余裕。",
          "example": "弁解の余地はない。"
        },
        {
          "term": "ひとかど",
          "reading": "ひとかど",
          "meaning": "一人前で優れていること。",
          "example": "彼も今ではひとかどの人物だ。"
        },
        {
          "term": "矢も盾もたまらない",
          "reading": "やもたてもたまらない",
          "meaning": "思いつめて、じっとしていられない。",
          "example": "結果が気になって、矢も盾もたまらない。"
        },
        {
          "term": "致命的",
          "reading": "ちめいてき",
          "meaning": "命にかかわるような。取り返しのつかない。",
          "example": "それは計画にとって致命的なミスだった。"
        },
        {
          "term": "老化",
          "reading": "ろうか",
          "meaning": "年をとって心身の働きが衰えること。",
          "example": "適度な運動は老化を防ぐ。"
        },
        {
          "term": "味気ない",
          "reading": "あじけない",
          "meaning": "面白みがない。つまらない。",
          "example": "一人での食事は味気ない。"
        },
        {
          "term": "度胸",
          "reading": "どきょう",
          "meaning": "物事に動じない心。",
          "example": "大勢の前でも堂々としていて度胸がある。"
        },
        {
          "term": "軽やか",
          "reading": "かろやか",
          "meaning": "身軽で動きが早い様子。",
          "example": "軽やかな足取りで歩く。"
        },
        {
          "term": "からくり",
          "reading": "からくり",
          "meaning": "仕掛け。仕組み。",
          "example": "手品のからくりを見破る。"
        },
        {
          "term": "しゃくりあげる",
          "reading": "しゃくりあげる",
          "meaning": "泣きじゃくって、息を吸い込むようにする。",
          "example": "子供がしゃくりあげて泣いている。"
        },
        {
          "term": "いたれりつくせり",
          "reading": "いたれりつくせり",
          "meaning": "配慮が完全に行き届いていること。",
          "example": "旅館のサービスはいたれりつくせりだった。"
        },
        {
          "term": "わだかまり",
          "reading": "わだかまり",
          "meaning": "心の中に残っている不信感や不満。",
          "example": "話し合いで心のわだかまりが消えた。"
        }
      ]
    },
    {
      "id": "DAY6",
      "label": "DAY 6",
      "items": [
        {
          "term": "自給自足",
          "reading": "じきゅうじそく",
          "meaning": "必要な物を自分で生産してまかなうこと。",
          "example": "田舎で自給自足の生活を送る。"
        },
        {
          "term": "弱肉強食",
          "reading": "じゃくにくきょうしょく",
          "meaning": "弱い者が強い者の犠牲になること。",
          "example": "自然界は弱肉強食の世界だ。"
        },
        {
          "term": "二人三脚",
          "reading": "ににんさんきゃく",
          "meaning": "二人で協力して物事を行うこと。",
          "example": "夫婦二人三脚で店を切り盛りする。"
        },
        {
          "term": "右往左往",
          "reading": "うおうさおう",
          "meaning": "混乱してあっちへ行ったりこっちへ行ったりすること。",
          "example": "突然の事故に右往左往する。"
        },
        {
          "term": "無我夢中",
          "reading": "むがむちゅう",
          "meaning": "我を忘れて熱中すること。",
          "example": "無我夢中でボールを追いかける。"
        },
        {
          "term": "百発百中",
          "reading": "ひゃっぱつひゃくちゅう",
          "meaning": "予想や計画がすべて当たること。",
          "example": "彼の予言は百発百中だ。"
        }
      ]
    },
    {
      "id": "WEEK12",
      "items": [
        {
          "term": "あえる",
          "reading": "あえる",
          "meaning": "食材に調味料などを混ぜ合わせる。",
          "example": "ほうれん草をごまであえる。"
        },
        {
          "term": "からめる",
          "reading": "からめる",
          "meaning": "粘り気のあるものをまとわせる。",
          "example": "ソースをパスタによくからめる。"
        },
        {
          "term": "まぶす",
          "reading": "まぶす",
          "meaning": "粉などを表面全体につける。",
          "example": "団子にきな粉をまぶす。"
        },
        {
          "term": "きざむ",
          "reading": "きざむ",
          "meaning": "細かく切る。",
          "example": "ネギを細かくきざむ。"
        },
        {
          "term": "する",
          "reading": "する",
          "meaning": "すり鉢などで細かく砕く。",
          "example": "ごまをする。"
        },
        {
          "term": "ねかす",
          "reading": "ねかす",
          "meaning": "食材をしばらくそのまま置いておく。",
          "example": "生地を冷蔵庫で一晩ねかす。"
        }
      ]
    }
  ]
}
